sc2simulator/__init__.py
sc2simulator/__main__.py
sc2simulator/__version__.py
sc2simulator/cli.py
sc2simulator/constants.py
sc2simulator/testCaseMgr.py
sc2simulator/mpqeditor_en/History.txt
sc2simulator/mpqeditor_en/Win32/MPQEditor.exe
sc2simulator/mpqeditor_en/x64/MPQEditor.exe
sc2simulator/scenarioMgr/__init__.py
sc2simulator/scenarioMgr/__main__.py
sc2simulator/scenarioMgr/bank.py
sc2simulator/scenarioMgr/functions.py
sc2simulator/scenarioMgr/scenario.py
sc2simulator/scenarioMgr/scenarioPlayer.py
sc2simulator/scenarioMgr/scenarioUnit.py
sc2simulator/setup/__init__.py
sc2simulator/setup/functions.py
sc2simulator/setup/mapLocations.py
sc2simulator/setup/simpleRaceMap.py
sc2simulator/setup/simpleSelection.py
sc2simulator/setup/treeSelection.py
sc2simulator/setup/unitSelection.py
sc2simulator-0.8.2.dist-info/METADATA
sc2simulator-0.8.2.dist-info/RECORD
sc2simulator-0.8.2.dist-info/WHEEL
sc2simulator-0.8.2.dist-info/entry_points.txt
sc2simulator-0.8.2.dist-info/top_level.txt
