Metadata-Version: 2.1
Name: sc2simulator
Version: 0.8.2
Summary: design, run and test desired situations using human, AI, bot or computer control
Home-page: https://github.com/ttinies/sc2simulator
Author: ttinies
Author-email: help.fool@versentiedge.com
License: Apache License 2.0
Platform: UNKNOWN
Classifier: License :: OSI Approved :: Apache Software License
Classifier: Programming Language :: Python
Classifier: Programming Language :: Python :: 3
Classifier: Programming Language :: Python :: 3.6
Classifier: Programming Language :: Python :: Implementation :: CPython
Classifier: Programming Language :: Python :: Implementation :: PyPy
Classifier: Topic :: Games/Entertainment :: Real Time Strategy
Classifier: Topic :: Scientific/Engineering :: Artificial Intelligence
Requires-Python: >3.4
Requires-Dist: sc2common
Requires-Dist: sc2gameLobby
Requires-Dist: sc2ladderMgmt
Requires-Dist: sc2maptool
Requires-Dist: sc2players
